[
  {
    "id": "p001",
    "name": "Robe midi fleurie taille smockée",
    "category": "vetements-pour-femmes",
    "price": 15.99,
    "originalPrice": 39.99,
    "discountPercent": 60,
    "rating": 4.6,
    "reviewCount": 1287,
    "colors": [
      {
        "name": "Rouge",
        "hex": "#E8393A",
        "image": "https://picsum.photos/seed/p001r/600/800"
      },
      {
        "name": "Noir",
        "hex": "#111111",
        "image": "https://picsum.photos/seed/p001n/600/800"
      },
      {
        "name": "Blanc",
        "hex": "#FFFFFF",
        "image": "https://picsum.photos/seed/p001b/600/800"
      }
    ],
    "sizes": [
      "XS",
      "S",
      "M",
      "L",
      "XL"
    ],
    "images": [
      "https://picsum.photos/seed/p001a/600/800",
      "https://picsum.photos/seed/p001b/600/800",
      "https://picsum.photos/seed/p001c/600/800"
    ],
    "badge": "BESTSELLER",
    "isTrending": true,
    "deliveryDays": 6,
    "description": "Robe légère à imprimé floral avec coupe flatteuse, idéale pour les sorties estivales.",
    "material": "100% polyester",
    "tags": [
      "robe",
      "fleurie",
      "été"
    ]
  },
  {
    "id": "p002",
    "name": "Top côtelé col carré minimaliste",
    "category": "vetements-pour-femmes",
    "price": 8.49,
    "originalPrice": 16.99,
    "discountPercent": 50,
    "rating": 4.5,
    "reviewCount": 954,
    "colors": [
      {
        "name": "Beige",
        "hex": "#D8C3A5"
      },
      {
        "name": "Noir",
        "hex": "#111111"
      },
      {
        "name": "Rose",
        "hex": "#F4A6B7"
      }
    ],
    "sizes": [
      "XS",
      "S",
      "M",
      "L"
    ],
    "images": [
      "https://picsum.photos/seed/p002a/600/800",
      "https://picsum.photos/seed/p002b/600/800"
    ],
    "badge": "NEW",
    "isTrending": false,
    "deliveryDays": 5,
    "description": "Top côtelé extensible au design épuré, parfait sous une veste ou seul.",
    "material": "95% coton, 5% élasthanne",
    "tags": [
      "top",
      "basique",
      "côtelé"
    ]
  },
  {
    "id": "p003",
    "name": "Jean wide leg taille haute brut",
    "category": "vetements-pour-femmes",
    "price": 21.99,
    "originalPrice": 44.99,
    "discountPercent": 51,
    "rating": 4.4,
    "reviewCount": 764,
    "colors": [
      {
        "name": "Bleu denim",
        "hex": "#3B5B92"
      },
      {
        "name": "Noir",
        "hex": "#111111"
      }
    ],
    "sizes": [
      "XS",
      "S",
      "M",
      "L",
      "XL",
      "XXL"
    ],
    "images": [
      "https://picsum.photos/seed/p003a/600/800",
      "https://picsum.photos/seed/p003b/600/800"
    ],
    "badge": null,
    "isTrending": true,
    "deliveryDays": 8,
    "description": "Jean large taille haute au tombé moderne avec effet allongeant.",
    "material": "78% coton, 20% polyester, 2% élasthanne",
    "tags": [
      "jean",
      "wide leg",
      "taille haute"
    ]
  },
  {
    "id": "p004",
    "name": "Bikini triangle texturé 2 pièces",
    "category": "vetements-pour-femmes",
    "price": 10.99,
    "originalPrice": 24.99,
    "discountPercent": 56,
    "rating": 4.7,
    "reviewCount": 2301,
    "colors": [
      {
        "name": "Corail",
        "hex": "#FF6B6B"
      },
      {
        "name": "Noir",
        "hex": "#111111"
      },
      {
        "name": "Turquoise",
        "hex": "#1ABCBE"
      }
    ],
    "sizes": [
      "XS",
      "S",
      "M",
      "L",
      "XL"
    ],
    "images": [
      "https://picsum.photos/seed/p004a/600/800",
      "https://picsum.photos/seed/p004b/600/800"
    ],
    "badge": "FLASH",
    "isTrending": true,
    "deliveryDays": 5,
    "description": "Bikini texturé à séchage rapide avec doublure douce et coupe ajustable.",
    "material": "82% nylon, 18% élasthanne",
    "tags": [
      "bikini",
      "plage",
      "vacances"
    ]
  },
  {
    "id": "p005",
    "name": "Chemise oversize satinée homme",
    "category": "vetements-pour-hommes",
    "price": 17.5,
    "originalPrice": 34.99,
    "discountPercent": 50,
    "rating": 4.2,
    "reviewCount": 428,
    "colors": [
      {
        "name": "Blanc",
        "hex": "#FFFFFF"
      },
      {
        "name": "Bleu ciel",
        "hex": "#8FCBFF"
      },
      {
        "name": "Noir",
        "hex": "#111111"
      }
    ],
    "sizes": [
      "S",
      "M",
      "L",
      "XL",
      "XXL"
    ],
    "images": [
      "https://picsum.photos/seed/p005a/600/800",
      "https://picsum.photos/seed/p005b/600/800"
    ],
    "badge": null,
    "isTrending": false,
    "deliveryDays": 7,
    "description": "Chemise fluide finition satinée avec col classique et coupe ample.",
    "material": "100% viscose",
    "tags": [
      "homme",
      "chemise",
      "oversize"
    ]
  },
  {
    "id": "p006",
    "name": "Ensemble pyjama satiné imprimé cœur",
    "category": "vetements-pour-femmes",
    "price": 13.99,
    "originalPrice": 29.99,
    "discountPercent": 53,
    "rating": 4.8,
    "reviewCount": 1570,
    "colors": [
      {
        "name": "Rose poudré",
        "hex": "#EFB8C8"
      },
      {
        "name": "Noir",
        "hex": "#111111"
      }
    ],
    "sizes": [
      "XS",
      "S",
      "M",
      "L",
      "XL"
    ],
    "images": [
      "https://picsum.photos/seed/p006a/600/800",
      "https://picsum.photos/seed/p006b/600/800"
    ],
    "badge": "BESTSELLER",
    "isTrending": true,
    "deliveryDays": 6,
    "description": "Pyjama satin doux avec top boutonné et short confortable.",
    "material": "97% polyester, 3% élasthanne",
    "tags": [
      "pyjama",
      "nuit",
      "satin"
    ]
  },
  {
    "id": "p007",
    "name": "Legging sport taille haute sculptant",
    "category": "vetements-pour-femmes",
    "price": 12.49,
    "originalPrice": 27.99,
    "discountPercent": 55,
    "rating": 4.6,
    "reviewCount": 1142,
    "colors": [
      {
        "name": "Noir",
        "hex": "#111111"
      },
      {
        "name": "Gris",
        "hex": "#8A8A8A"
      },
      {
        "name": "Prune",
        "hex": "#6F2C91"
      }
    ],
    "sizes": [
      "XS",
      "S",
      "M",
      "L",
      "XL"
    ],
    "images": [
      "https://picsum.photos/seed/p007a/600/800",
      "https://picsum.photos/seed/p007b/600/800"
    ],
    "badge": "NEW",
    "isTrending": true,
    "deliveryDays": 5,
    "description": "Legging gainant respirant conçu pour le running et la salle.",
    "material": "75% nylon, 25% élasthanne",
    "tags": [
      "sport",
      "legging",
      "fitness"
    ]
  },
  {
    "id": "p008",
    "name": "Robe portefeuille grande taille à pois",
    "category": "vetements-pour-femmes",
    "price": 18.99,
    "originalPrice": 42.99,
    "discountPercent": 56,
    "rating": 4.5,
    "reviewCount": 832,
    "colors": [
      {
        "name": "Noir",
        "hex": "#111111"
      },
      {
        "name": "Marine",
        "hex": "#1D3557"
      }
    ],
    "sizes": [
      "L",
      "XL",
      "XXL"
    ],
    "images": [
      "https://picsum.photos/seed/p008a/600/800",
      "https://picsum.photos/seed/p008b/600/800"
    ],
    "badge": null,
    "isTrending": false,
    "deliveryDays": 7,
    "description": "Robe portefeuille chic avec imprimé pois et ceinture à nouer.",
    "material": "100% polyester",
    "tags": [
      "grande taille",
      "robe",
      "pois"
    ]
  },
  {
    "id": "p009",
    "name": "Sandales plates bride dorée",
    "category": "chaussures",
    "price": 11.99,
    "originalPrice": 28.99,
    "discountPercent": 59,
    "rating": 4.3,
    "reviewCount": 649,
    "colors": [
      {
        "name": "Or",
        "hex": "#C9A227"
      },
      {
        "name": "Noir",
        "hex": "#111111"
      },
      {
        "name": "Beige",
        "hex": "#D8C3A5"
      }
    ],
    "sizes": [
      "S",
      "M",
      "L",
      "XL"
    ],
    "images": [
      "https://picsum.photos/seed/p009a/600/800",
      "https://picsum.photos/seed/p009b/600/800"
    ],
    "badge": "FLASH",
    "isTrending": true,
    "deliveryDays": 6,
    "description": "Sandales légères à bride métallisée et semelle souple.",
    "material": "PU et caoutchouc",
    "tags": [
      "chaussures",
      "sandales",
      "été"
    ]
  },
  {
    "id": "p010",
    "name": "Collier multi-rangs perles dorées",
    "category": "bijoux-accessoires",
    "price": 4.99,
    "originalPrice": 12.99,
    "discountPercent": 62,
    "rating": 4.4,
    "reviewCount": 733,
    "colors": [
      {
        "name": "Doré",
        "hex": "#C9A227"
      }
    ],
    "sizes": [
      "XS",
      "S",
      "M"
    ],
    "images": [
      "https://picsum.photos/seed/p010a/600/800",
      "https://picsum.photos/seed/p010b/600/800"
    ],
    "badge": "BESTSELLER",
    "isTrending": false,
    "deliveryDays": 5,
    "description": "Collier superposé avec finition brillante et perles modernes.",
    "material": "Alliage de zinc",
    "tags": [
      "bijoux",
      "collier",
      "doré"
    ]
  },
  {
    "id": "p011",
    "name": "Set housse de coussin bouclette x2",
    "category": "bijoux-accessoires",
    "price": 9.49,
    "originalPrice": 22.99,
    "discountPercent": 59,
    "rating": 4.6,
    "reviewCount": 401,
    "colors": [
      {
        "name": "Crème",
        "hex": "#F6F1E9"
      },
      {
        "name": "Terracotta",
        "hex": "#C46B4D"
      }
    ],
    "sizes": [
      "M",
      "L"
    ],
    "images": [
      "https://picsum.photos/seed/p011a/600/800",
      "https://picsum.photos/seed/p011b/600/800"
    ],
    "badge": null,
    "isTrending": false,
    "deliveryDays": 8,
    "description": "Lot de 2 housses cosy au toucher doux pour salon chaleureux.",
    "material": "100% polyester",
    "tags": [
      "maison",
      "déco",
      "coussin"
    ]
  },
  {
    "id": "p012",
    "name": "Mini enceinte Bluetooth portable",
    "category": "bijoux-accessoires",
    "price": 18.49,
    "originalPrice": 39.99,
    "discountPercent": 54,
    "rating": 4.1,
    "reviewCount": 280,
    "colors": [
      {
        "name": "Noir",
        "hex": "#111111"
      },
      {
        "name": "Bleu",
        "hex": "#3A86FF"
      },
      {
        "name": "Rose",
        "hex": "#F4A6B7"
      }
    ],
    "sizes": [
      "XS",
      "S",
      "M"
    ],
    "images": [
      "https://picsum.photos/seed/p012a/600/800",
      "https://picsum.photos/seed/p012b/600/800"
    ],
    "badge": "NEW",
    "isTrending": true,
    "deliveryDays": 5,
    "description": "Enceinte compacte avec autonomie 10h et son stéréo puissant.",
    "material": "ABS + composants électroniques",
    "tags": [
      "audio",
      "bluetooth",
      "portable"
    ]
  },
  {
    "id": "p013",
    "name": "Body bébé coton bio lot de 3",
    "category": "vetements-pour-femmes",
    "price": 12.99,
    "originalPrice": 25.99,
    "discountPercent": 50,
    "rating": 4.8,
    "reviewCount": 640,
    "colors": [
      {
        "name": "Blanc",
        "hex": "#FFFFFF"
      },
      {
        "name": "Sauge",
        "hex": "#9DB8A1"
      }
    ],
    "sizes": [
      "XS",
      "S",
      "M"
    ],
    "images": [
      "https://picsum.photos/seed/p013a/600/800",
      "https://picsum.photos/seed/p013b/600/800"
    ],
    "badge": "BESTSELLER",
    "isTrending": false,
    "deliveryDays": 6,
    "description": "Bodies doux et respirants avec ouverture pratique pressionnée.",
    "material": "100% coton biologique",
    "tags": [
      "bébé",
      "coton",
      "essentiels"
    ]
  },
  {
    "id": "p014",
    "name": "Sneakers enfant semelle légère",
    "category": "vetements-pour-femmes",
    "price": 14.49,
    "originalPrice": 31.99,
    "discountPercent": 55,
    "rating": 4.3,
    "reviewCount": 322,
    "colors": [
      {
        "name": "Blanc",
        "hex": "#FFFFFF"
      },
      {
        "name": "Rose",
        "hex": "#F4A6B7"
      },
      {
        "name": "Bleu",
        "hex": "#3A86FF"
      }
    ],
    "sizes": [
      "XS",
      "S",
      "M",
      "L"
    ],
    "images": [
      "https://picsum.photos/seed/p014a/600/800",
      "https://picsum.photos/seed/p014b/600/800"
    ],
    "badge": null,
    "isTrending": false,
    "deliveryDays": 7,
    "description": "Sneakers confortables et souples pour les journées actives.",
    "material": "Mesh + caoutchouc",
    "tags": [
      "enfant",
      "chaussures",
      "sport"
    ]
  },
  {
    "id": "p015",
    "name": "Sérum éclat vitamine C 30ml",
    "category": "bijoux-accessoires",
    "price": 7.99,
    "originalPrice": 19.99,
    "discountPercent": 60,
    "rating": 4.5,
    "reviewCount": 918,
    "colors": [
      {
        "name": "Transparent",
        "hex": "#FDF2E9"
      }
    ],
    "sizes": [
      "XS",
      "S"
    ],
    "images": [
      "https://picsum.photos/seed/p015a/600/800",
      "https://picsum.photos/seed/p015b/600/800"
    ],
    "badge": "FLASH",
    "isTrending": true,
    "deliveryDays": 5,
    "description": "Sérum illuminateur à la vitamine C pour un teint visiblement uniforme.",
    "material": "Formule cosmétique",
    "tags": [
      "beauté",
      "soin",
      "visage"
    ]
  },
  {
    "id": "p016",
    "name": "Robe chemise ceinturée rayée",
    "category": "vetements-pour-femmes",
    "price": 19.99,
    "originalPrice": 41.99,
    "discountPercent": 52,
    "rating": 4.4,
    "reviewCount": 532,
    "colors": [
      {
        "name": "Bleu",
        "hex": "#4F6FA5"
      },
      {
        "name": "Blanc",
        "hex": "#FFFFFF"
      }
    ],
    "sizes": [
      "S",
      "M",
      "L",
      "XL"
    ],
    "images": [
      "https://picsum.photos/seed/p016a/600/800",
      "https://picsum.photos/seed/p016b/600/800"
    ],
    "badge": null,
    "isTrending": false,
    "deliveryDays": 6,
    "description": "Robe chemise élégante à rayures fines avec ceinture assortie.",
    "material": "65% coton, 35% polyester",
    "tags": [
      "robe",
      "chemise",
      "rayures"
    ]
  },
  {
    "id": "p017",
    "name": "Top dos nu satiné drapé",
    "category": "vetements-pour-femmes",
    "price": 11.99,
    "originalPrice": 26.99,
    "discountPercent": 56,
    "rating": 4.7,
    "reviewCount": 1430,
    "colors": [
      {
        "name": "Champagne",
        "hex": "#E5CDA7"
      },
      {
        "name": "Noir",
        "hex": "#111111"
      },
      {
        "name": "Vert émeraude",
        "hex": "#0B6E4F"
      }
    ],
    "sizes": [
      "XS",
      "S",
      "M",
      "L"
    ],
    "images": [
      "https://picsum.photos/seed/p017a/600/800",
      "https://picsum.photos/seed/p017b/600/800"
    ],
    "badge": "BESTSELLER",
    "isTrending": true,
    "deliveryDays": 5,
    "description": "Top drapé au rendu satiné, idéal pour une tenue de soirée.",
    "material": "98% polyester, 2% élasthanne",
    "tags": [
      "top",
      "soirée",
      "satin"
    ]
  },
  {
    "id": "p018",
    "name": "Pantalon cargo taille élastique",
    "category": "vetements-pour-femmes",
    "price": 16.99,
    "originalPrice": 35.99,
    "discountPercent": 53,
    "rating": 4.2,
    "reviewCount": 490,
    "colors": [
      {
        "name": "Kaki",
        "hex": "#6B7A4A"
      },
      {
        "name": "Noir",
        "hex": "#111111"
      }
    ],
    "sizes": [
      "XS",
      "S",
      "M",
      "L",
      "XL"
    ],
    "images": [
      "https://picsum.photos/seed/p018a/600/800",
      "https://picsum.photos/seed/p018b/600/800"
    ],
    "badge": "NEW",
    "isTrending": false,
    "deliveryDays": 7,
    "description": "Pantalon cargo confortable avec poches utilitaires.",
    "material": "100% coton",
    "tags": [
      "pantalon",
      "cargo",
      "street"
    ]
  },
  {
    "id": "p019",
    "name": "Maillot une pièce asymétrique",
    "category": "vetements-pour-femmes",
    "price": 12.99,
    "originalPrice": 28.99,
    "discountPercent": 55,
    "rating": 4.5,
    "reviewCount": 610,
    "colors": [
      {
        "name": "Noir",
        "hex": "#111111"
      },
      {
        "name": "Fuchsia",
        "hex": "#DD2D75"
      }
    ],
    "sizes": [
      "S",
      "M",
      "L",
      "XL"
    ],
    "images": [
      "https://picsum.photos/seed/p019a/600/800",
      "https://picsum.photos/seed/p019b/600/800"
    ],
    "badge": "FLASH",
    "isTrending": true,
    "deliveryDays": 5,
    "description": "Maillot asymétrique moderne avec maintien confortable.",
    "material": "80% polyamide, 20% élasthanne",
    "tags": [
      "plage",
      "maillot",
      "été"
    ]
  },
  {
    "id": "p020",
    "name": "Kimono plage imprimé tropical",
    "category": "vetements-pour-femmes",
    "price": 9.99,
    "originalPrice": 21.99,
    "discountPercent": 55,
    "rating": 4.3,
    "reviewCount": 388,
    "colors": [
      {
        "name": "Multicolore",
        "hex": "#FF8C42"
      }
    ],
    "sizes": [
      "S",
      "M",
      "L"
    ],
    "images": [
      "https://picsum.photos/seed/p020a/600/800",
      "https://picsum.photos/seed/p020b/600/800"
    ],
    "badge": null,
    "isTrending": false,
    "deliveryDays": 6,
    "description": "Kimono léger imprimé tropical, parfait au-dessus d'un maillot.",
    "material": "100% polyester",
    "tags": [
      "kimono",
      "plage",
      "vacances"
    ]
  },
  {
    "id": "p021",
    "name": "T-shirt oversize manches tombantes",
    "category": "vetements-pour-hommes",
    "price": 8.99,
    "originalPrice": 18.99,
    "discountPercent": 53,
    "rating": 4.1,
    "reviewCount": 351,
    "colors": [
      {
        "name": "Blanc",
        "hex": "#FFFFFF"
      },
      {
        "name": "Noir",
        "hex": "#111111"
      },
      {
        "name": "Sable",
        "hex": "#C8B28D"
      }
    ],
    "sizes": [
      "S",
      "M",
      "L",
      "XL",
      "XXL"
    ],
    "images": [
      "https://picsum.photos/seed/p021a/600/800",
      "https://picsum.photos/seed/p021b/600/800"
    ],
    "badge": "NEW",
    "isTrending": false,
    "deliveryDays": 5,
    "description": "T-shirt ample et respirant pour un style casual quotidien.",
    "material": "100% coton",
    "tags": [
      "homme",
      "tshirt",
      "oversize"
    ]
  },
  {
    "id": "p022",
    "name": "Short chino coupe slim",
    "category": "vetements-pour-hommes",
    "price": 14.99,
    "originalPrice": 31.99,
    "discountPercent": 53,
    "rating": 4.4,
    "reviewCount": 299,
    "colors": [
      {
        "name": "Beige",
        "hex": "#D8C3A5"
      },
      {
        "name": "Marine",
        "hex": "#1D3557"
      }
    ],
    "sizes": [
      "S",
      "M",
      "L",
      "XL"
    ],
    "images": [
      "https://picsum.photos/seed/p022a/600/800",
      "https://picsum.photos/seed/p022b/600/800"
    ],
    "badge": null,
    "isTrending": false,
    "deliveryDays": 7,
    "description": "Short chino polyvalent, coupe slim et finition propre.",
    "material": "97% coton, 3% élasthanne",
    "tags": [
      "short",
      "chino",
      "été"
    ]
  },
  {
    "id": "p023",
    "name": "Brassière sport maintien medium",
    "category": "vetements-pour-femmes",
    "price": 10.49,
    "originalPrice": 24.99,
    "discountPercent": 58,
    "rating": 4.6,
    "reviewCount": 1201,
    "colors": [
      {
        "name": "Noir",
        "hex": "#111111"
      },
      {
        "name": "Lavande",
        "hex": "#A78BFA"
      },
      {
        "name": "Vert sauge",
        "hex": "#9DB8A1"
      }
    ],
    "sizes": [
      "XS",
      "S",
      "M",
      "L",
      "XL"
    ],
    "images": [
      "https://picsum.photos/seed/p023a/600/800",
      "https://picsum.photos/seed/p023b/600/800"
    ],
    "badge": "BESTSELLER",
    "isTrending": true,
    "deliveryDays": 5,
    "description": "Brassière respirante avec maintien moyen et bretelles douces.",
    "material": "78% nylon, 22% élasthanne",
    "tags": [
      "sport",
      "brassière",
      "yoga"
    ]
  },
  {
    "id": "p024",
    "name": "Veste coupe-vent légère",
    "category": "vetements-pour-femmes",
    "price": 20.99,
    "originalPrice": 45.99,
    "discountPercent": 54,
    "rating": 4.3,
    "reviewCount": 432,
    "colors": [
      {
        "name": "Noir",
        "hex": "#111111"
      },
      {
        "name": "Blanc",
        "hex": "#FFFFFF"
      }
    ],
    "sizes": [
      "S",
      "M",
      "L",
      "XL"
    ],
    "images": [
      "https://picsum.photos/seed/p024a/600/800",
      "https://picsum.photos/seed/p024b/600/800"
    ],
    "badge": "FLASH",
    "isTrending": false,
    "deliveryDays": 6,
    "description": "Veste coupe-vent pliable et déperlante pour l'extérieur.",
    "material": "100% polyester",
    "tags": [
      "running",
      "veste",
      "extérieur"
    ]
  },
  {
    "id": "p025",
    "name": "Robe bodycon grande taille côtelée",
    "category": "vetements-pour-femmes",
    "price": 17.49,
    "originalPrice": 36.99,
    "discountPercent": 53,
    "rating": 4.5,
    "reviewCount": 711,
    "colors": [
      {
        "name": "Noir",
        "hex": "#111111"
      },
      {
        "name": "Bordeaux",
        "hex": "#6D071A"
      }
    ],
    "sizes": [
      "L",
      "XL",
      "XXL"
    ],
    "images": [
      "https://picsum.photos/seed/p025a/600/800",
      "https://picsum.photos/seed/p025b/600/800"
    ],
    "badge": "NEW",
    "isTrending": true,
    "deliveryDays": 7,
    "description": "Robe côtelée extensible qui épouse la silhouette.",
    "material": "90% polyester, 10% élasthanne",
    "tags": [
      "grande taille",
      "bodycon",
      "soirée"
    ]
  },
  {
    "id": "p026",
    "name": "Blazer long grande taille croisé",
    "category": "vetements-pour-femmes",
    "price": 24.99,
    "originalPrice": 52.99,
    "discountPercent": 53,
    "rating": 4.2,
    "reviewCount": 288,
    "colors": [
      {
        "name": "Noir",
        "hex": "#111111"
      },
      {
        "name": "Camel",
        "hex": "#B08968"
      }
    ],
    "sizes": [
      "L",
      "XL",
      "XXL"
    ],
    "images": [
      "https://picsum.photos/seed/p026a/600/800",
      "https://picsum.photos/seed/p026b/600/800"
    ],
    "badge": null,
    "isTrending": false,
    "deliveryDays": 8,
    "description": "Blazer structuré à double boutonnage pour un look chic.",
    "material": "98% polyester, 2% élasthanne",
    "tags": [
      "blazer",
      "grande taille",
      "bureau"
    ]
  },
  {
    "id": "p027",
    "name": "Sandales plateforme tressées",
    "category": "chaussures",
    "price": 18.99,
    "originalPrice": 39.99,
    "discountPercent": 53,
    "rating": 4.4,
    "reviewCount": 560,
    "colors": [
      {
        "name": "Naturel",
        "hex": "#C8AD7F"
      },
      {
        "name": "Noir",
        "hex": "#111111"
      }
    ],
    "sizes": [
      "S",
      "M",
      "L",
      "XL"
    ],
    "images": [
      "https://picsum.photos/seed/p027a/600/800",
      "https://picsum.photos/seed/p027b/600/800"
    ],
    "badge": "BESTSELLER",
    "isTrending": true,
    "deliveryDays": 6,
    "description": "Sandales plateforme effet tressé avec semelle confortable.",
    "material": "PU et jute",
    "tags": [
      "chaussures",
      "plateforme",
      "été"
    ]
  },
  {
    "id": "p028",
    "name": "Escarpins vernis bout pointu",
    "category": "chaussures",
    "price": 22.49,
    "originalPrice": 47.99,
    "discountPercent": 53,
    "rating": 4.1,
    "reviewCount": 223,
    "colors": [
      {
        "name": "Rouge",
        "hex": "#E8393A"
      },
      {
        "name": "Noir",
        "hex": "#111111"
      }
    ],
    "sizes": [
      "S",
      "M",
      "L"
    ],
    "images": [
      "https://picsum.photos/seed/p028a/600/800",
      "https://picsum.photos/seed/p028b/600/800"
    ],
    "badge": "FLASH",
    "isTrending": false,
    "deliveryDays": 7,
    "description": "Escarpins élégants à finition vernie et talon fin.",
    "material": "PU",
    "tags": [
      "escarpins",
      "soirée",
      "femme"
    ]
  },
  {
    "id": "p029",
    "name": "Sac bandoulière matelassé chaîne",
    "category": "bijoux-accessoires",
    "price": 13.49,
    "originalPrice": 29.99,
    "discountPercent": 55,
    "rating": 4.6,
    "reviewCount": 1040,
    "colors": [
      {
        "name": "Noir",
        "hex": "#111111"
      },
      {
        "name": "Crème",
        "hex": "#F6F1E9"
      },
      {
        "name": "Rouge",
        "hex": "#E8393A"
      }
    ],
    "sizes": [
      "XS",
      "S",
      "M"
    ],
    "images": [
      "https://picsum.photos/seed/p029a/600/800",
      "https://picsum.photos/seed/p029b/600/800"
    ],
    "badge": "NEW",
    "isTrending": true,
    "deliveryDays": 5,
    "description": "Sac chic matelassé avec chaîne dorée réglable.",
    "material": "PU",
    "tags": [
      "sac",
      "accessoire",
      "matelassé"
    ]
  },
  {
    "id": "p030",
    "name": "Boucles d'oreilles créoles épaisses",
    "category": "bijoux-accessoires",
    "price": 3.99,
    "originalPrice": 9.99,
    "discountPercent": 60,
    "rating": 4.5,
    "reviewCount": 812,
    "colors": [
      {
        "name": "Doré",
        "hex": "#C9A227"
      },
      {
        "name": "Argent",
        "hex": "#BFC5CE"
      }
    ],
    "sizes": [
      "XS",
      "S"
    ],
    "images": [
      "https://picsum.photos/seed/p030a/600/800",
      "https://picsum.photos/seed/p030b/600/800"
    ],
    "badge": null,
    "isTrending": false,
    "deliveryDays": 5,
    "description": "Créoles épaisses intemporelles, finition brillante.",
    "material": "Alliage de zinc",
    "tags": [
      "bijoux",
      "boucles",
      "créoles"
    ]
  },
  {
    "id": "p031",
    "name": "Parure de lit 2 places coton lavé",
    "category": "bijoux-accessoires",
    "price": 23.99,
    "originalPrice": 54.99,
    "discountPercent": 56,
    "rating": 4.7,
    "reviewCount": 505,
    "colors": [
      {
        "name": "Blanc",
        "hex": "#FFFFFF"
      },
      {
        "name": "Sauge",
        "hex": "#9DB8A1"
      }
    ],
    "sizes": [
      "M",
      "L",
      "XL"
    ],
    "images": [
      "https://picsum.photos/seed/p031a/600/800",
      "https://picsum.photos/seed/p031b/600/800"
    ],
    "badge": "BESTSELLER",
    "isTrending": false,
    "deliveryDays": 8,
    "description": "Parure douce et respirante pour une chambre apaisante.",
    "material": "100% coton",
    "tags": [
      "linge de lit",
      "maison",
      "coton"
    ]
  },
  {
    "id": "p032",
    "name": "Lampe de table LED minimaliste",
    "category": "bijoux-accessoires",
    "price": 16.99,
    "originalPrice": 38.99,
    "discountPercent": 56,
    "rating": 4.2,
    "reviewCount": 190,
    "colors": [
      {
        "name": "Noir",
        "hex": "#111111"
      },
      {
        "name": "Blanc",
        "hex": "#FFFFFF"
      }
    ],
    "sizes": [
      "S",
      "M"
    ],
    "images": [
      "https://picsum.photos/seed/p032a/600/800",
      "https://picsum.photos/seed/p032b/600/800"
    ],
    "badge": "NEW",
    "isTrending": false,
    "deliveryDays": 7,
    "description": "Lampe LED compacte à intensité réglable, style contemporain.",
    "material": "ABS + aluminium",
    "tags": [
      "maison",
      "lampe",
      "bureau"
    ]
  },
  {
    "id": "p033",
    "name": "Écouteurs sans fil TWS",
    "category": "bijoux-accessoires",
    "price": 19.99,
    "originalPrice": 44.99,
    "discountPercent": 56,
    "rating": 4.3,
    "reviewCount": 610,
    "colors": [
      {
        "name": "Noir",
        "hex": "#111111"
      },
      {
        "name": "Blanc",
        "hex": "#FFFFFF"
      }
    ],
    "sizes": [
      "XS",
      "S"
    ],
    "images": [
      "https://picsum.photos/seed/p033a/600/800",
      "https://picsum.photos/seed/p033b/600/800"
    ],
    "badge": "FLASH",
    "isTrending": true,
    "deliveryDays": 5,
    "description": "Écouteurs Bluetooth avec micro HD et boîtier recharge.",
    "material": "ABS + électronique",
    "tags": [
      "audio",
      "écouteurs",
      "tws"
    ]
  },
  {
    "id": "p034",
    "name": "Support téléphone voiture magnétique",
    "category": "bijoux-accessoires",
    "price": 6.99,
    "originalPrice": 15.99,
    "discountPercent": 56,
    "rating": 4.0,
    "reviewCount": 275,
    "colors": [
      {
        "name": "Noir",
        "hex": "#111111"
      }
    ],
    "sizes": [
      "XS"
    ],
    "images": [
      "https://picsum.photos/seed/p034a/600/800",
      "https://picsum.photos/seed/p034b/600/800"
    ],
    "badge": null,
    "isTrending": false,
    "deliveryDays": 6,
    "description": "Support magnétique compact avec rotation 360°.",
    "material": "ABS + aimant",
    "tags": [
      "auto",
      "téléphone",
      "accessoire"
    ]
  },
  {
    "id": "p035",
    "name": "Robe grossesse côtelée manche courte",
    "category": "vetements-pour-femmes",
    "price": 14.99,
    "originalPrice": 32.99,
    "discountPercent": 55,
    "rating": 4.6,
    "reviewCount": 477,
    "colors": [
      {
        "name": "Noir",
        "hex": "#111111"
      },
      {
        "name": "Taupe",
        "hex": "#A68A7A"
      }
    ],
    "sizes": [
      "S",
      "M",
      "L",
      "XL"
    ],
    "images": [
      "https://picsum.photos/seed/p035a/600/800",
      "https://picsum.photos/seed/p035b/600/800"
    ],
    "badge": "NEW",
    "isTrending": false,
    "deliveryDays": 7,
    "description": "Robe grossesse extensible et confortable pour le quotidien.",
    "material": "92% coton, 8% élasthanne",
    "tags": [
      "maternité",
      "robe",
      "confort"
    ]
  },
  {
    "id": "p036",
    "name": "Sac à langer multifonction",
    "category": "vetements-pour-femmes",
    "price": 21.49,
    "originalPrice": 46.99,
    "discountPercent": 54,
    "rating": 4.4,
    "reviewCount": 362,
    "colors": [
      {
        "name": "Gris",
        "hex": "#8A8A8A"
      },
      {
        "name": "Noir",
        "hex": "#111111"
      }
    ],
    "sizes": [
      "M",
      "L"
    ],
    "images": [
      "https://picsum.photos/seed/p036a/600/800",
      "https://picsum.photos/seed/p036b/600/800"
    ],
    "badge": "BESTSELLER",
    "isTrending": true,
    "deliveryDays": 6,
    "description": "Sac à langer spacieux avec poches isothermes.",
    "material": "Oxford imperméable",
    "tags": [
      "bébé",
      "sac",
      "maternité"
    ]
  },
  {
    "id": "p037",
    "name": "Ensemble enfant t-shirt + short",
    "category": "vetements-pour-femmes",
    "price": 11.49,
    "originalPrice": 25.99,
    "discountPercent": 56,
    "rating": 4.5,
    "reviewCount": 509,
    "colors": [
      {
        "name": "Bleu",
        "hex": "#3A86FF"
      },
      {
        "name": "Corail",
        "hex": "#FF6B6B"
      }
    ],
    "sizes": [
      "XS",
      "S",
      "M",
      "L"
    ],
    "images": [
      "https://picsum.photos/seed/p037a/600/800",
      "https://picsum.photos/seed/p037b/600/800"
    ],
    "badge": "FLASH",
    "isTrending": false,
    "deliveryDays": 6,
    "description": "Set léger et pratique pour les activités d'été.",
    "material": "100% coton",
    "tags": [
      "enfant",
      "ensemble",
      "été"
    ]
  },
  {
    "id": "p038",
    "name": "Robe tutu fille à paillettes",
    "category": "vetements-pour-femmes",
    "price": 13.99,
    "originalPrice": 30.99,
    "discountPercent": 55,
    "rating": 4.7,
    "reviewCount": 288,
    "colors": [
      {
        "name": "Rose",
        "hex": "#F4A6B7"
      },
      {
        "name": "Lilac",
        "hex": "#C4A5FF"
      }
    ],
    "sizes": [
      "XS",
      "S",
      "M"
    ],
    "images": [
      "https://picsum.photos/seed/p038a/600/800",
      "https://picsum.photos/seed/p038b/600/800"
    ],
    "badge": "NEW",
    "isTrending": true,
    "deliveryDays": 7,
    "description": "Robe festive avec jupe en tulle et détails scintillants.",
    "material": "Polyester + tulle",
    "tags": [
      "fille",
      "robe",
      "fête"
    ]
  },
  {
    "id": "p039",
    "name": "Palette ombres à paupières nude",
    "category": "bijoux-accessoires",
    "price": 8.49,
    "originalPrice": 18.99,
    "discountPercent": 55,
    "rating": 4.3,
    "reviewCount": 738,
    "colors": [
      {
        "name": "Nude",
        "hex": "#D8B08C"
      }
    ],
    "sizes": [
      "XS"
    ],
    "images": [
      "https://picsum.photos/seed/p039a/600/800",
      "https://picsum.photos/seed/p039b/600/800"
    ],
    "badge": "BESTSELLER",
    "isTrending": true,
    "deliveryDays": 5,
    "description": "Palette 12 teintes mates et irisées pour look quotidien.",
    "material": "Formule cosmétique",
    "tags": [
      "maquillage",
      "palette",
      "yeux"
    ]
  },
  {
    "id": "p040",
    "name": "Brosse lissante ionique",
    "category": "bijoux-accessoires",
    "price": 17.99,
    "originalPrice": 39.99,
    "discountPercent": 55,
    "rating": 4.1,
    "reviewCount": 214,
    "colors": [
      {
        "name": "Noir",
        "hex": "#111111"
      },
      {
        "name": "Rose",
        "hex": "#F4A6B7"
      }
    ],
    "sizes": [
      "S"
    ],
    "images": [
      "https://picsum.photos/seed/p040a/600/800",
      "https://picsum.photos/seed/p040b/600/800"
    ],
    "badge": null,
    "isTrending": false,
    "deliveryDays": 6,
    "description": "Brosse chauffante rapide avec effet anti-frisottis.",
    "material": "ABS + céramique",
    "tags": [
      "cheveux",
      "beauty",
      "outil"
    ]
  },
  {
    "id": "p041",
    "name": "Sweat à capuche imprimé graphique",
    "category": "vetements-pour-femmes",
    "price": 14.99,
    "originalPrice": 34.99,
    "discountPercent": 57,
    "rating": 4.4,
    "reviewCount": 690,
    "colors": [
      {
        "name": "Noir",
        "hex": "#111111"
      },
      {
        "name": "Blanc",
        "hex": "#FFFFFF"
      }
    ],
    "sizes": [
      "S",
      "M",
      "L",
      "XL"
    ],
    "images": [
      "https://picsum.photos/seed/p041a/600/800",
      "https://picsum.photos/seed/p041b/600/800"
    ],
    "badge": "FLASH",
    "isTrending": true,
    "deliveryDays": 5,
    "description": "Hoodie confortable avec print tendance et coupe droite.",
    "material": "80% coton, 20% polyester",
    "tags": [
      "promo",
      "sweat",
      "casual"
    ]
  },
  {
    "id": "p042",
    "name": "Robe satinée fendue midi",
    "category": "vetements-pour-femmes",
    "price": 22.99,
    "originalPrice": 49.99,
    "discountPercent": 54,
    "rating": 4.6,
    "reviewCount": 904,
    "colors": [
      {
        "name": "Vert",
        "hex": "#0B6E4F"
      },
      {
        "name": "Champagne",
        "hex": "#E5CDA7"
      }
    ],
    "sizes": [
      "XS",
      "S",
      "M",
      "L"
    ],
    "images": [
      "https://picsum.photos/seed/p042a/600/800",
      "https://picsum.photos/seed/p042b/600/800"
    ],
    "badge": "NEW",
    "isTrending": true,
    "deliveryDays": 6,
    "description": "Robe satinée fluide avec fente élégante.",
    "material": "97% polyester, 3% élasthanne",
    "tags": [
      "nouveauté",
      "robe",
      "soirée"
    ]
  },
  {
    "id": "p043",
    "name": "Lot de 5 chaussettes sport unisexes",
    "category": "vetements-pour-femmes",
    "price": 6.49,
    "originalPrice": 14.99,
    "discountPercent": 57,
    "rating": 4.2,
    "reviewCount": 418,
    "colors": [
      {
        "name": "Multicolore",
        "hex": "#999999"
      }
    ],
    "sizes": [
      "S",
      "M",
      "L"
    ],
    "images": [
      "https://picsum.photos/seed/p043a/600/800",
      "https://picsum.photos/seed/p043b/600/800"
    ],
    "badge": null,
    "isTrending": false,
    "deliveryDays": 3,
    "description": "Pack respirant et extensible pour usage quotidien.",
    "material": "72% coton, 25% polyester, 3% élasthanne",
    "tags": [
      "livraison rapide",
      "chaussettes",
      "sport"
    ]
  },
  {
    "id": "p044",
    "name": "Combinaison short imprimé tropical",
    "category": "vetements-pour-femmes",
    "price": 15.49,
    "originalPrice": 33.99,
    "discountPercent": 54,
    "rating": 4.3,
    "reviewCount": 369,
    "colors": [
      {
        "name": "Orange",
        "hex": "#FF8C42"
      },
      {
        "name": "Bleu",
        "hex": "#3A86FF"
      }
    ],
    "sizes": [
      "S",
      "M",
      "L",
      "XL"
    ],
    "images": [
      "https://picsum.photos/seed/p044a/600/800",
      "https://picsum.photos/seed/p044b/600/800"
    ],
    "badge": "FLASH",
    "isTrending": true,
    "deliveryDays": 5,
    "description": "Combishort léger pour look vacances instantané.",
    "material": "100% viscose",
    "tags": [
      "combinaison",
      "été",
      "femme"
    ]
  },
  {
    "id": "p045",
    "name": "Débardeur côtelé homme lot de 2",
    "category": "vetements-pour-hommes",
    "price": 9.99,
    "originalPrice": 21.99,
    "discountPercent": 55,
    "rating": 4.3,
    "reviewCount": 332,
    "colors": [
      {
        "name": "Blanc",
        "hex": "#FFFFFF"
      },
      {
        "name": "Noir",
        "hex": "#111111"
      }
    ],
    "sizes": [
      "S",
      "M",
      "L",
      "XL",
      "XXL"
    ],
    "images": [
      "https://picsum.photos/seed/p045a/600/800",
      "https://picsum.photos/seed/p045b/600/800"
    ],
    "badge": null,
    "isTrending": false,
    "deliveryDays": 4,
    "description": "Lot de débardeurs stretch, coupe ajustée.",
    "material": "95% coton, 5% élasthanne",
    "tags": [
      "homme",
      "débardeur",
      "essentiels"
    ]
  },
  {
    "id": "p046",
    "name": "Nuisette dentelle satin contrasté",
    "category": "vetements-pour-femmes",
    "price": 9.49,
    "originalPrice": 22.99,
    "discountPercent": 59,
    "rating": 4.7,
    "reviewCount": 1188,
    "colors": [
      {
        "name": "Noir",
        "hex": "#111111"
      },
      {
        "name": "Rouge",
        "hex": "#E8393A"
      }
    ],
    "sizes": [
      "XS",
      "S",
      "M",
      "L",
      "XL"
    ],
    "images": [
      "https://picsum.photos/seed/p046a/600/800",
      "https://picsum.photos/seed/p046b/600/800"
    ],
    "badge": "BESTSELLER",
    "isTrending": true,
    "deliveryDays": 5,
    "description": "Nuisette satinée avec détails dentelle raffinés.",
    "material": "95% polyester, 5% élasthanne",
    "tags": [
      "nuit",
      "dentelle",
      "femme"
    ]
  },
  {
    "id": "p047",
    "name": "Short sport 2-en-1 respirant",
    "category": "vetements-pour-femmes",
    "price": 13.49,
    "originalPrice": 29.99,
    "discountPercent": 55,
    "rating": 4.4,
    "reviewCount": 412,
    "colors": [
      {
        "name": "Noir",
        "hex": "#111111"
      },
      {
        "name": "Vert",
        "hex": "#2A9D8F"
      }
    ],
    "sizes": [
      "S",
      "M",
      "L",
      "XL"
    ],
    "images": [
      "https://picsum.photos/seed/p047a/600/800",
      "https://picsum.photos/seed/p047b/600/800"
    ],
    "badge": "NEW",
    "isTrending": false,
    "deliveryDays": 6,
    "description": "Short double couche avec poche téléphone intégrée.",
    "material": "88% polyester, 12% élasthanne",
    "tags": [
      "sport",
      "short",
      "running"
    ]
  },
  {
    "id": "p048",
    "name": "Manteau long grande taille ceinturé",
    "category": "vetements-pour-femmes",
    "price": 29.99,
    "originalPrice": 64.99,
    "discountPercent": 54,
    "rating": 4.1,
    "reviewCount": 206,
    "colors": [
      {
        "name": "Camel",
        "hex": "#B08968"
      },
      {
        "name": "Noir",
        "hex": "#111111"
      }
    ],
    "sizes": [
      "L",
      "XL",
      "XXL"
    ],
    "images": [
      "https://picsum.photos/seed/p048a/600/800",
      "https://picsum.photos/seed/p048b/600/800"
    ],
    "badge": null,
    "isTrending": false,
    "deliveryDays": 8,
    "description": "Manteau structuré avec ceinture pour silhouette élégante.",
    "material": "100% polyester",
    "tags": [
      "manteau",
      "grande taille",
      "hiver"
    ]
  },
  {
    "id": "p049",
    "name": "Mules à talons carrés minimalistes",
    "category": "chaussures",
    "price": 17.49,
    "originalPrice": 37.99,
    "discountPercent": 54,
    "rating": 4.2,
    "reviewCount": 284,
    "colors": [
      {
        "name": "Beige",
        "hex": "#D8C3A5"
      },
      {
        "name": "Noir",
        "hex": "#111111"
      }
    ],
    "sizes": [
      "S",
      "M",
      "L"
    ],
    "images": [
      "https://picsum.photos/seed/p049a/600/800",
      "https://picsum.photos/seed/p049b/600/800"
    ],
    "badge": "FLASH",
    "isTrending": false,
    "deliveryDays": 7,
    "description": "Mules élégantes à talon carré, confort quotidien.",
    "material": "PU",
    "tags": [
      "mules",
      "chaussures",
      "talons"
    ]
  },
  {
    "id": "p050",
    "name": "Lunettes de soleil cat-eye",
    "category": "bijoux-accessoires",
    "price": 5.99,
    "originalPrice": 13.99,
    "discountPercent": 57,
    "rating": 4.5,
    "reviewCount": 772,
    "colors": [
      {
        "name": "Noir",
        "hex": "#111111"
      },
      {
        "name": "Écaille",
        "hex": "#8B5E3C"
      }
    ],
    "sizes": [
      "XS"
    ],
    "images": [
      "https://picsum.photos/seed/p050a/600/800",
      "https://picsum.photos/seed/p050b/600/800"
    ],
    "badge": "BESTSELLER",
    "isTrending": true,
    "deliveryDays": 5,
    "description": "Monture cat-eye tendance avec protection UV400.",
    "material": "PC",
    "tags": [
      "lunettes",
      "accessoires",
      "soleil"
    ]
  },
  {
    "id": "p051",
    "name": "Tapis salon motif géométrique",
    "category": "bijoux-accessoires",
    "price": 19.49,
    "originalPrice": 42.99,
    "discountPercent": 55,
    "rating": 4.3,
    "reviewCount": 336,
    "colors": [
      {
        "name": "Ivoire",
        "hex": "#F6F1E9"
      },
      {
        "name": "Gris",
        "hex": "#8A8A8A"
      }
    ],
    "sizes": [
      "M",
      "L",
      "XL"
    ],
    "images": [
      "https://picsum.photos/seed/p051a/600/800",
      "https://picsum.photos/seed/p051b/600/800"
    ],
    "badge": null,
    "isTrending": false,
    "deliveryDays": 8,
    "description": "Tapis doux antidérapant au design moderne.",
    "material": "Polypropylène",
    "tags": [
      "maison",
      "tapis",
      "déco"
    ]
  },
  {
    "id": "p052",
    "name": "Caméra mini Wi-Fi intérieure",
    "category": "bijoux-accessoires",
    "price": 24.99,
    "originalPrice": 54.99,
    "discountPercent": 55,
    "rating": 4.0,
    "reviewCount": 167,
    "colors": [
      {
        "name": "Blanc",
        "hex": "#FFFFFF"
      }
    ],
    "sizes": [
      "XS"
    ],
    "images": [
      "https://picsum.photos/seed/p052a/600/800",
      "https://picsum.photos/seed/p052b/600/800"
    ],
    "badge": "NEW",
    "isTrending": false,
    "deliveryDays": 6,
    "description": "Caméra connectée avec vision nocturne et détection de mouvement.",
    "material": "ABS + électronique",
    "tags": [
      "smart home",
      "camera",
      "sécurité"
    ]
  },
  {
    "id": "p053",
    "name": "Poussette canne compacte",
    "category": "vetements-pour-femmes",
    "price": 49.99,
    "originalPrice": 109.99,
    "discountPercent": 55,
    "rating": 4.2,
    "reviewCount": 201,
    "colors": [
      {
        "name": "Noir",
        "hex": "#111111"
      },
      {
        "name": "Gris",
        "hex": "#8A8A8A"
      }
    ],
    "sizes": [
      "M",
      "L"
    ],
    "images": [
      "https://picsum.photos/seed/p053a/600/800",
      "https://picsum.photos/seed/p053b/600/800"
    ],
    "badge": "FLASH",
    "isTrending": true,
    "deliveryDays": 7,
    "description": "Poussette légère pliage rapide, idéale en déplacement.",
    "material": "Aluminium + textile",
    "tags": [
      "bébé",
      "poussette",
      "sortie"
    ]
  },
  {
    "id": "p054",
    "name": "Sac à dos scolaire enfant",
    "category": "vetements-pour-femmes",
    "price": 12.99,
    "originalPrice": 27.99,
    "discountPercent": 54,
    "rating": 4.4,
    "reviewCount": 429,
    "colors": [
      {
        "name": "Bleu",
        "hex": "#3A86FF"
      },
      {
        "name": "Rose",
        "hex": "#F4A6B7"
      }
    ],
    "sizes": [
      "S",
      "M"
    ],
    "images": [
      "https://picsum.photos/seed/p054a/600/800",
      "https://picsum.photos/seed/p054b/600/800"
    ],
    "badge": null,
    "isTrending": false,
    "deliveryDays": 6,
    "description": "Sac ergonomique avec compartiments et bretelles rembourrées.",
    "material": "Oxford",
    "tags": [
      "école",
      "enfant",
      "sac"
    ]
  },
  {
    "id": "p055",
    "name": "Rouge à lèvres mat longue tenue",
    "category": "bijoux-accessoires",
    "price": 4.49,
    "originalPrice": 9.99,
    "discountPercent": 55,
    "rating": 4.6,
    "reviewCount": 1320,
    "colors": [
      {
        "name": "Rouge classique",
        "hex": "#B80F0A"
      },
      {
        "name": "Nude",
        "hex": "#C77D67"
      }
    ],
    "sizes": [
      "XS"
    ],
    "images": [
      "https://picsum.photos/seed/p055a/600/800",
      "https://picsum.photos/seed/p055b/600/800"
    ],
    "badge": "BESTSELLER",
    "isTrending": true,
    "deliveryDays": 5,
    "description": "Texture velours et couleur intense sans transfert.",
    "material": "Formule cosmétique",
    "tags": [
      "maquillage",
      "lèvres",
      "mat"
    ]
  },
  {
    "id": "p056",
    "name": "Robe trapèze imprimé pois rétro",
    "category": "vetements-pour-femmes",
    "price": 16.49,
    "originalPrice": 35.99,
    "discountPercent": 54,
    "rating": 4.3,
    "reviewCount": 517,
    "colors": [
      {
        "name": "Marine",
        "hex": "#1D3557"
      },
      {
        "name": "Rouge",
        "hex": "#E8393A"
      }
    ],
    "sizes": [
      "XS",
      "S",
      "M",
      "L",
      "XL"
    ],
    "images": [
      "https://picsum.photos/seed/p056a/600/800",
      "https://picsum.photos/seed/p056b/600/800"
    ],
    "badge": null,
    "isTrending": false,
    "deliveryDays": 6,
    "description": "Robe trapèze au style rétro et coupe confortable.",
    "material": "100% polyester",
    "tags": [
      "robe",
      "rétro",
      "pois"
    ]
  },
  {
    "id": "p057",
    "name": "Veste en jean courte délavée",
    "category": "vetements-pour-femmes",
    "price": 23.49,
    "originalPrice": 49.99,
    "discountPercent": 53,
    "rating": 4.5,
    "reviewCount": 660,
    "colors": [
      {
        "name": "Bleu clair",
        "hex": "#7EA8BE"
      },
      {
        "name": "Noir",
        "hex": "#111111"
      }
    ],
    "sizes": [
      "XS",
      "S",
      "M",
      "L"
    ],
    "images": [
      "https://picsum.photos/seed/p057a/600/800",
      "https://picsum.photos/seed/p057b/600/800"
    ],
    "badge": "NEW",
    "isTrending": true,
    "deliveryDays": 5,
    "description": "Veste en jean crop à finition délavée tendance.",
    "material": "78% coton, 22% polyester",
    "tags": [
      "veste",
      "denim",
      "nouveauté"
    ]
  },
  {
    "id": "p058",
    "name": "Top de bain manches longues UV",
    "category": "vetements-pour-femmes",
    "price": 14.49,
    "originalPrice": 31.99,
    "discountPercent": 55,
    "rating": 4.4,
    "reviewCount": 401,
    "colors": [
      {
        "name": "Noir",
        "hex": "#111111"
      },
      {
        "name": "Bleu marine",
        "hex": "#1D3557"
      }
    ],
    "sizes": [
      "S",
      "M",
      "L",
      "XL"
    ],
    "images": [
      "https://picsum.photos/seed/p058a/600/800",
      "https://picsum.photos/seed/p058b/600/800"
    ],
    "badge": "FLASH",
    "isTrending": false,
    "deliveryDays": 5,
    "description": "Top anti-UV idéal pour les sports de plage.",
    "material": "82% nylon, 18% élasthanne",
    "tags": [
      "plage",
      "anti uv",
      "sport"
    ]
  },
  {
    "id": "p059",
    "name": "Combinaison pyjama animal adorable",
    "category": "bijoux-accessoires",
    "price": 8.99,
    "originalPrice": 19.99,
    "discountPercent": 55,
    "rating": 4.1,
    "reviewCount": 155,
    "colors": [
      {
        "name": "Jaune",
        "hex": "#F4D35E"
      },
      {
        "name": "Rose",
        "hex": "#F4A6B7"
      }
    ],
    "sizes": [
      "XS",
      "S",
      "M"
    ],
    "images": [
      "https://picsum.photos/seed/p059a/600/800",
      "https://picsum.photos/seed/p059b/600/800"
    ],
    "badge": "NEW",
    "isTrending": false,
    "deliveryDays": 7,
    "description": "Tenue mignonne pour animaux de compagnie, matière douce.",
    "material": "Polaire polyester",
    "tags": [
      "animal",
      "vêtement",
      "pet"
    ]
  },
  {
    "id": "p060",
    "name": "Collier pour chien anti-traction",
    "category": "bijoux-accessoires",
    "price": 6.99,
    "originalPrice": 14.99,
    "discountPercent": 53,
    "rating": 4.5,
    "reviewCount": 243,
    "colors": [
      {
        "name": "Noir",
        "hex": "#111111"
      },
      {
        "name": "Rouge",
        "hex": "#E8393A"
      },
      {
        "name": "Bleu",
        "hex": "#3A86FF"
      }
    ],
    "sizes": [
      "S",
      "M",
      "L",
      "XL"
    ],
    "images": [
      "https://picsum.photos/seed/p060a/600/800",
      "https://picsum.photos/seed/p060b/600/800"
    ],
    "badge": "BESTSELLER",
    "isTrending": true,
    "deliveryDays": 6,
    "description": "Collier réglable robuste avec fermeture sécurisée.",
    "material": "Nylon renforcé",
    "tags": [
      "animal",
      "chien",
      "accessoire"
    ]
  }
]